PyGeoCN/__init__.py
PyGeoCN/china_city.geojson
PyGeoCN/china_district.geojson
PyGeoCN/china_province.geojson
PyGeoCN/regeo.py
pygeo_cn-0.1.5.dist-info/LICENSE
pygeo_cn-0.1.5.dist-info/METADATA
pygeo_cn-0.1.5.dist-info/WHEEL
pygeo_cn-0.1.5.dist-info/top_level.txt
pygeo_cn-0.1.5.dist-info/RECORD
