Metadata-Version: 2.1
Name: pygeo_cn
Version: 0.1.5
Summary: Provides the function of offline processing of reverse geocoding of longitude and latitude coordinates in China, using longitude and latitude coordinates to query geographical location information (including location and administrative codes), with the finest granularity down to district and county-level cities
Home-page: https://github.com/CZD-MO/PyGeoCN
Author: czd
Author-email: caozuodong666@gmail.com
Classifier: Programming Language :: Python :: 3
Classifier: License :: OSI Approved :: MIT License
Classifier: Operating System :: OS Independent
Requires-Python: >=3.6
License-File: LICENSE
Requires-Dist: geopandas
Requires-Dist: shapely
